{
    "@class": "com.kony.gen.viz.model.component.KVizLabel",
    "DNDConfig": null,
    "__parentReadjusting__": false,
    "_height_": {
        "type": "ref",
        "value": "preferred"
    },
    "_left_": {
        "type": "string",
        "value": "110dp"
    },
    "_margin_": [
        1,
        1,
        1,
        1
    ],
    "_padding_": [
        0,
        0,
        0,
        0
    ],
    "_skin_": "s57ab9d565104a1787cf15e28cae9269",
    "_text_": "BIRTHDAY",
    "_top_": {
        "type": "string",
        "value": "245dp"
    },
    "_width_": {
        "type": "ref",
        "value": "preferred"
    },
    "_wrapping_": 2,
    "android": {
        "textStyle": {
            "letterSpacing": 0,
            "strikeThrough": false
        }
    },
    "canUpdateUI": true,
    "containerweight": 100,
    "contentalignment": 4,
    "id": "lblc2",
    "info": null,
    "ipad": {
        "psp": {
            "wrapping": 2
        }
    },
    "iphone": {
        "psp": {
            "wrapping": 2
        }
    },
    "iscustomlayout": false,
    "isvisible": true,
    "kuid": "a6928864434f42f9b0ddf87d931e9bfd",
    "name": "kony.ui.Label",
    "parent": "flxGraphKA",
    "pf": "frmDashboardKA",
    "retaincontentalignment": false,
    "retainflexpositionproperties": false,
    "tooltip": "",
    "wType": "Label",
    "zindex": 1
}