{
    "@class": "com.kony.gen.viz.model.component.KVizTextBox2",
    "DNDConfig": null,
    "__parentReadjusting__": false,
    "_height_": {
        "type": "string",
        "value": "40dp"
    },
    "_left_": {
        "type": "string",
        "value": "30dp"
    },
    "_margin_": [
        0,
        0,
        0,
        0
    ],
    "_padding_": [
        2,
        0,
        0,
        0
    ],
    "_placeholder_": "Enter a description",
    "_skin_": "sbad3c0dbd09447ea3f81eebcfc69002",
    "_text_": "",
    "_top_": {
        "type": "string",
        "value": "0dp"
    },
    "_width_": {
        "type": "string",
        "value": "45.16%"
    },
    "autocapitalize": "none",
    "autocomplete": false,
    "autocorrect": false,
    "autofilter": false,
    "canUpdateUI": true,
    "centery": {
        "type": "string",
        "value": "50%"
    },
    "containerheight": "",
    "containerheightmode": 1,
    "containerweight": 100,
    "contentalignment": 4,
    "desktopweb": {
        "psp": {
            "hoverSkin": "s80a8c5539a441ee9b9b49917cc45cc2"
        }
    },
    "focusskin": "s80a8c5539a441ee9b9b49917cc45cc2",
    "id": "tbxCategoryDesc",
    "info": null,
    "isvisible": true,
    "keyboardtype": "A",
    "kuid": "g05840424e9e4501aab39d51f95ee2f5",
    "mode": "A",
    "name": "kony.ui.TextBox2",
    "paddinginpixel": false,
    "parent": "CopyflxExpenseName0fa8aa9e7f1a34c",
    "pf": "frmAddCategoryKA",
    "securetextentry": false,
    "textinputmode": "A",
    "tooltip": "",
    "viewtype": "default",
    "wType": "TextField",
    "zindex": 1
}