{
  "android": {
    "font_size": 36,
    "isForked": false
  },
  "background_color": "00000000",
  "bg_type": "one",
  "border_color": "72727233",
  "border_radius": 2,
  "border_style": "custom",
  "border_type": 0,
  "border_width": 1,
  "desktopweb": {
    "font_name": "Lato-Regular",
    "font_size": 125,
    "isForked": false
  },
  "fontSizeInPx": true,
  "font_color": "4a4a4aff",
  "font_name": "Helvetica",
  "font_size": 125,
  "font_style": "normal",
  "font_weight": "normal",
  "ipad": {
    "font_size": 54,
    "isForked": false
  },
  "iphone": {
    "font_size": 54,
    "isForked": false
  },
  "isDefaultSkin": true,
  "kiosk": {
    "font_size": 94,
    "isForked": false
  },
  "kuid": "sa8931d21c78443195a881b65efcfdff",
  "spaan": {
    "font_size": 125,
    "isForked": false
  },
  "spaandroidtablet": {
    "font_size": 125,
    "isForked": false
  },
  "spabb": {
    "font_size": 125,
    "isForked": false
  },
  "spaip": {
    "font_size": 125,
    "isForked": false
  },
  "spaipad": {
    "font_size": 125,
    "isForked": false
  },
  "spawindowstablet": {
    "font_size": 125,
    "isForked": false
  },
  "spawinphone8": {
    "font_size": 125,
    "isForked": false
  },
  "tabrcandroid": {
    "font_size": 89,
    "isForked": false
  },
  "wType": "Calendar",
  "watchos": {
    "font_size": 54,
    "isForked": false
  },
  "windows8": {
    "font_size": 37,
    "isForked": false
  },
  "winphone8": {
    "font_size": 50,
    "isForked": false
  }
}