{
  "android": {
    "font_name": "Helvetica",
    "font_size": 45,
    "isForked": false
  },
  "background_color": "00000000",
  "bg_type": "one",
  "border_color": "424242ff",
  "border_style": "plain",
  "border_type": 0,
  "border_width": 0,
  "delinkedPltfrms": {
    "desktop": [
      "desktopweb"
    ],
    "mobile": [],
    "tablet": [
      "spaipad"
    ],
    "watch": []
  },
  "desktopweb": {
    "font_name": "Lato-Regular",
    "font_size": 108,
    "isForked": true
  },
  "fontSizeInPx": true,
  "font_color": "4242427f",
  "font_name": "Helvetica",
  "font_size": 79,
  "font_style": "normal",
  "font_weight": "normal",
  "ipad": {
    "font_name": "Helvetica",
    "font_size": 68,
    "isForked": false
  },
  "iphone": {
    "font_name": "Helvetica",
    "font_size": 68,
    "isForked": false
  },
  "isDefaultSkin": false,
  "kiosk": {
    "font_name": "GenericMonospace",
    "font_size": 119,
    "isForked": false
  },
  "kuid": "sd5458b630124839ac94c56d4eb567ec",
  "spaan": {
    "font_name": "Lato-Regular",
    "font_size": 79,
    "isForked": false
  },
  "spaandroidtablet": {
    "font_name": "Lato-Regular",
    "font_size": 79,
    "isForked": false
  },
  "spabb": {
    "font_name": "Helvetica",
    "font_size": 79,
    "isForked": false
  },
  "spaip": {
    "font_name": "Lato-Regular",
    "font_size": 79,
    "isForked": false
  },
  "spaipad": {
    "font_name": "Lato-Regular",
    "font_size": 108,
    "isForked": true
  },
  "spawindowstablet": {
    "font_name": "Helvetica",
    "font_size": 79,
    "isForked": false
  },
  "spawinphone8": {
    "font_name": "Helvetica",
    "font_size": 79,
    "isForked": false
  },
  "tabrcandroid": {
    "font_name": "Helvetica",
    "font_size": 113,
    "isForked": false
  },
  "wType": "Label",
  "watchos": {
    "font_name": "Helvetica",
    "font_size": 68,
    "isForked": false
  },
  "windows8": {
    "font_name": "GenericMonospace",
    "font_size": 46,
    "isForked": false
  },
  "winphone8": {
    "font_name": "GenericMonospace",
    "font_size": 63,
    "isForked": false
  }
}