{
    "@class": "com.kony.gen.viz.model.container.KVizScrollFlexForm",
    "DNDConfig": null,
    "_margin_": [
        0,
        0,
        0,
        0
    ],
    "_orientation_": 1,
    "_padding_": [
        0,
        0,
        0,
        0
    ],
    "_percent_": true,
    "_skin_": "scb1c33fe4434d12a9cdad33f6799736",
    "_title_": null,
    "addWidgetsdone": false,
    "allboxes": [],
    "canUpdateUI": true,
    "canvasWidth": 518,
    "children": [
        "flxEmployeeTracking"
    ],
    "containerId": true,
    "containerweight": 100,
    "currentLocale": "default",
    "device": "desktopweb",
    "displayorientation": 3,
    "enabledforidletimeout": false,
    "id": "segEmployeeList",
    "info": null,
    "initdone": false,
    "inputaccessoryviewtype": 4,
    "intransitionconfig": {
        "formTransition": "None"
    },
    "iscustomlayout": false,
    "isvisible": true,
    "kuid": "bfa9c1b065074127b29dc96468d5dae7",
    "name": "kony.ui.Form2",
    "needappmenu": true,
    "outtransitionconfig": {
        "formTransition": "None"
    },
    "paddinginpixel": false,
    "platform": "desktopweb",
    "prevDevice": "desktopweb",
    "prevPlatform": "desktopweb",
    "retaincontentalignment": false,
    "retainflexpositionproperties": false,
    "retainscrollposition": false,
    "shellCSS": "desktop",
    "titlebar": true,
    "type": 3,
    "wType": "Form"
}